{
    "name": "Api\\Objects\\Channel",
    "description": "See the fields returned by the read channel endpoint.",
    "version": "1.0.0+",
    "from_class": null,
    "extends": null,
    "typed": null,
    "url": "https:\/\/developer.apple.com\/documentation\/apple_news\/channel",
    "properties": [
        {
            "name": "createdAt",
            "type": "date-time",
            "required": false,
            "description": "The date and time the channel was created.",
            "typed": false
        },
        {
            "name": "id",
            "type": "uuid",
            "required": false,
            "description": "The unique identifier of the channel.",
            "typed": false
        },
        {
            "name": "modifiedAt",
            "type": "date-time",
            "required": false,
            "description": "The date and time the channel was last modified.",
            "typed": false
        },
        {
            "name": "name",
            "type": "string",
            "required": false,
            "description": "The name of the channel.",
            "typed": false
        },
        {
            "name": "shareUrl",
            "type": "string",
            "required": false,
            "description": "The URL to the channel within the News app. The shareUrl field applies only on devices with iOS 9 installed.",
            "typed": false
        },
        {
            "name": "type",
            "type": "string",
            "required": false,
            "description": "The channel.",
            "typed": false
        },
        {
            "name": "website",
            "type": "string",
            "required": false,
            "description": "The website that corresponds to this channel.",
            "typed": false
        }
    ]
}